pytunneling/__init__.py
pytunneling/__main__.py
pytunneling/logging.ini
pytunneling/pytunneling.py
pytunneling-0.0.2.dist-info/LICENSE
pytunneling-0.0.2.dist-info/METADATA
pytunneling-0.0.2.dist-info/WHEEL
pytunneling-0.0.2.dist-info/top_level.txt
pytunneling-0.0.2.dist-info/RECORD
