Metadata-Version: 2.1
Name: pytunneling
Version: 0.0.2
Summary: Python module that allows multi-hop SSH tunneling/port-forwarding
Home-page: https://github.com/mattykay/pytunneling
Author: Matthew Kalnins
Author-email: pytunneling@matthewkalnins.com
License: UNKNOWN
Keywords: ssh,tunneling,networking
Platform: UNKNOWN
Classifier: Programming Language :: Python
Classifier: Programming Language :: Python :: 3
Classifier: Programming Language :: Python :: 3.6
Classifier: Programming Language :: Python :: 3.7
Classifier: Programming Language :: Python :: 3.8
Classifier: License :: OSI Approved :: MIT License
Classifier: Operating System :: OS Independent
Classifier: Natural Language :: English
Classifier: Topic :: System :: Networking
Requires-Python: >=3.6
